{
  "name": "Points/new/1775210635663_LIV 1 Dadun.pdf",
  "bucket": "apitherapyv2-staging-storage",
  "metageneration": 1,
  "generation": 1779826097266,
  "contentType": "application/pdf",
  "storageClass": "STANDARD",
  "downloadTokens": [
    "5789aea1-2fa8-402a-9589-3b73dc090690"
  ],
  "etag": "O09c1sDq0ryIVGOo655ST7TBabA",
  "customMetadata": {
    "x-goog-reserved-source-generation": "1775210643060051"
  },
  "timeCreated": "2026-05-26T20:08:17.266Z",
  "updated": "2026-05-26T20:08:17.266Z",
  "size": 6185811,
  "md5Hash": "ueC/+ywohT+0Wwy5UIWyyA==",
  "crc32c": "542142730"
}